{
    "name": "Shotgun"
}{
    "name": "Manual"
}{
    "name": "парва"
}{
    "name": "вапрвапр"
}{
    "name": "вапрва"
}{
    "name": "кенапр"
}{
    "name": "вапирапр"
}{
    "name": "вапрвапр"
}{
    "name": "Принтер",
    "email": "пропр",
    "header": "пропр",
    "message": "пропрьпрь"
}{
    "name": "6575"
}{
    "name": "567567"
}{
    "name": "sadf"
}{
    "name": "cxvb"
}{
    "name": "df"
}{
    "student_name": "df"
}{
    "name": "ewrtewr"
}{
    "name": "wertwert"
}{
    "name": "ertewrt"
}{
    "course_name": "wertwert",
    "student_name": "ertewrt"
}{
    "name": "Shotgun"
}{
    "name": "Manual"
}{
    "name": "Вася"
}{
    "course_name": "Manual",
    "student_name": "Вася"
}{
    "name": "Shotgun"
}{
    "name": "Manual"
}{
    "name": "Вася"
}{
    "course_name": "Manual",
    "student_name": "Вася"
}